climate_module/__init__.py
climate_module/__main__.py
climate_module/core.py
climate_module/options.py
climate_module/provider.py
climate_module/hansel2020/__init__.py
climate_module/hansel2020/inputs.py
climate_module/hansel2020/model.py
climate_module/hansel2020/parameters.py
climate_module/resources/SSP markers ratio non_CO2 to CO2.csv
climate_module/resources/__init__.py
climate_module/resources/hansel FFI.csv
dice_climate_simulator-1.0.0.dist-info/LICENSE
dice_climate_simulator-1.0.0.dist-info/METADATA
dice_climate_simulator-1.0.0.dist-info/WHEEL
dice_climate_simulator-1.0.0.dist-info/entry_points.txt
dice_climate_simulator-1.0.0.dist-info/top_level.txt
dice_climate_simulator-1.0.0.dist-info/RECORD
