Metadata-Version: 2.1
Name: dice-climate-simulator
Version: 1.0.0
Summary: Generic DICE simulations: climate module
Author-email: Anna Shchiptsova <shchipts@iiasa.ac.at>
License: Copyright (c) 2022 International Institute for Applied Systems Analysis
Project-URL: Source, https://github.com/shchipts/generic-dice/tree/master/python/climate-module
Classifier: Development Status :: 5 - Production/Stable
Classifier: Intended Audience :: Science/Research
Classifier: Topic :: Scientific/Engineering :: Physics
Classifier: License :: OSI Approved :: MIT License
Classifier: Programming Language :: Python :: 3
Requires-Python: >=3.8
License-File: LICENSE
